twoblock/__init__.py
twoblock/_preproc_utilities.py
twoblock/robcent.py
twoblock/test_twoblock.py
twoblock/twoblock.py
twoblock/utils.py
twoblock-0.0.1.dist-info/LICENSE
twoblock-0.0.1.dist-info/METADATA
twoblock-0.0.1.dist-info/WHEEL
twoblock-0.0.1.dist-info/top_level.txt
twoblock-0.0.1.dist-info/RECORD
