Metadata-Version: 2.1
Name: twoblock
Version: 0.0.1
Summary: A Scikit-Learn Compatible Library for Simultaneous Two-Block Sufficient Dimension Reduction Methods
Home-page: https://github.com/SvenSerneels/twoblock
Author: Sven Serneels
Author-email: svenserneels@gmail.com
Classifier: Programming Language :: Python :: 3
Classifier: License :: OSI Approved :: MIT License
Classifier: Operating System :: OS Independent
License-File: LICENSE
Requires-Dist: numpy>=1.22.0
Requires-Dist: scipy>=1.8.0
Requires-Dist: scikit-learn>=1.3.0
Requires-Dist: pandas>=1.4.0
